README.md
setup.py
onelya_sdk/__init__.py
onelya_sdk/api.py
onelya_sdk/exceptions.py
onelya_sdk/session.py
onelya_sdk/utils.py
onelya_sdk.egg-info/PKG-INFO
onelya_sdk.egg-info/SOURCES.txt
onelya_sdk.egg-info/dependency_links.txt
onelya_sdk.egg-info/requires.txt
onelya_sdk.egg-info/top_level.txt
onelya_sdk/aeroexpress/__init__.py
onelya_sdk/aeroexpress/info/__init__.py
onelya_sdk/aeroexpress/reservation/__init__.py
onelya_sdk/aeroexpress/reservation/requests.py
onelya_sdk/aeroexpress/search/__init__.py
onelya_sdk/railway/__init__.py
onelya_sdk/railway/additional_meal/__init__.py
onelya_sdk/railway/additional_meal/requests.py
onelya_sdk/railway/info/__init__.py
onelya_sdk/railway/reservation/__init__.py
onelya_sdk/railway/reservation/requests.py
onelya_sdk/railway/search/__init__.py
onelya_sdk/references/__init__.py
onelya_sdk/wrapper/__init__.py
onelya_sdk/wrapper/requests.py
onelya_sdk/wrapper/types.py