Metadata-Version: 1.1
Name: onelya-sdk
Version: 1.3.8
Summary: Onelya Python SDK
Home-page: https://github.com/tmconsulting/onelya-python-sdk
Author: Travel Managment Consulting
Author-email: otd@tm-consulting.ru
License: MIT License
Download-URL: https://github.com/tmconsulting/onelya-python-sdk/archive/1.3.8.tar.gz
Platform: UNKNOWN
Classifier: Environment :: Web Environment
Classifier: Intended Audience :: Developers
Classifier: License :: OSI Approved :: MIT License
Classifier: Programming Language :: Python :: 3.6
Classifier: Topic :: Software Development :: Libraries :: Python Modules
